[
    {
        "judul": "Pencuri Kayu Jati di Hutan Produksi Wilayah Malang Ditangkap",
        "kategori": "Rejogja",
        "waktu_publish": "12 May 2024, 19:29",
        "waktu_scraping": "2024-05-12 19:33:37",
        "url": "https://rejogja.republika.co.id/berita/sddhce432/pencuri-kayu-jati-di-hutan-produksi-wilayah-malang-ditangkap"
    },
    {
        "judul": "Hamas: Beberapa Sandera Tewas Akibat Pengeboman Israel",
        "kategori": "Internasional",
        "waktu_publish": "12 May 2024, 19:25",
        "waktu_scraping": "2024-05-12 19:33:37",
        "url": "https://internasional.republika.co.id/berita/sddh6f488/hamas-beberapa-sandera-tewas-akibat-pengeboman-israel"
    },
    {
        "judul": "Isak Tangis Keluarga dan Kerabat Iringi Pemakaman Enam Korban Kecelakaan Bus Ciater",
        "kategori": "Visual",
        "waktu_publish": "12 May 2024, 19:24",
        "waktu_scraping": "2024-05-12 19:33:37",
        "url": "https://visual.republika.co.id/berita/sddh4f375/isak-tangis-keluarga-dan-kerabat-iringi-pemakaman-enam-korban-kecelakaan-bus-ciater"
    },
    {
        "judul": "Pemerintah Diimbau Buat Peraturan yang Memperketat Izin Study Tour Sekolah",
        "kategori": "News",
        "waktu_publish": "12 May 2024, 19:22",
        "waktu_scraping": "2024-05-12 19:33:37",
        "url": "https://news.republika.co.id/berita/sddh0t425/pemerintah-diimbau-buat-peraturan-yang-memperketat-izin-study-tour-sekolah"
    },
    {
        "judul": "Rumah Zakat Distribusikan Bantuan Pangan di Wilayah Terisolir Lebak Banten",
        "kategori": "Khazanah",
        "waktu_publish": "12 May 2024, 19:20",
        "waktu_scraping": "2024-05-12 19:33:37",
        "url": "https://khazanah.republika.co.id/berita/sddgyw463/rumah-zakat-distribusikan-bantuan-pangan-di-wilayah-terisolir-lebak-banten"
    },
    {
        "judul": "Media: AS Tawarkan Data Rahasia agar Israel tak Serang Penuh Rafah",
        "kategori": "Internasional",
        "waktu_publish": "12 May 2024, 19:19",
        "waktu_scraping": "2024-05-12 19:33:37",
        "url": "https://internasional.republika.co.id/berita/sddgwu488/media-as-tawarkan-data-rahasia-agar-israel-tak-serang-penuh-rafah"
    },
    {
        "judul": "Layanan Penukaran Uang Riyal untuk Jamaah Calon Haji",
        "kategori": "Visual",
        "waktu_publish": "12 May 2024, 19:18",
        "waktu_scraping": "2024-05-12 19:33:37",
        "url": "https://visual.republika.co.id/berita/sddgu6375/layanan-penukaran-uang-riyal-untuk-jamaah-calon-haji"
    },
    {
        "judul": "Pengusaha Bali Senang dengan Pelatihan P3K Bagi Pemandu Selam",
        "kategori": "Network",
        "waktu_publish": "12 May 2024, 19:13",
        "waktu_scraping": "2024-05-12 19:33:37",
        "url": "https://ruzka.republika.co.id/gaya-hidup/1674643807/pengusaha-bali-senang-dengan-pelatihan-p3k-bagi-pemandu-selam"
    },
    {
        "judul": "Israel Klaim Bangun RS Baru di Jalur Gaza Bagian Tengah",
        "kategori": "Internasional",
        "waktu_publish": "12 May 2024, 19:11",
        "waktu_scraping": "2024-05-12 19:33:37",
        "url": "https://internasional.republika.co.id/berita/sddgiq488/israel-klaim-bangun-rs-baru-di-jalur-gaza-bagian-tengah"
    },
    {
        "judul": "Peringati Mother\u2019s Day 2024, AGP Arthakes Gelar Health Talkshow",
        "kategori": "Ekonomi",
        "waktu_publish": "12 May 2024, 19:05",
        "waktu_scraping": "2024-05-12 19:33:37",
        "url": "https://ekonomi.republika.co.id/berita/sddg94463/peringati-mothers-day-2024-agp-arthakes-gelar-health-talkshow"
    },
    {
        "judul": "Penyebab Suhu Panas di Bengkulu, Ternyata karena Ada \u2018Gangguan\u2019 di Hindia Barat",
        "kategori": "News",
        "waktu_publish": "12 May 2024, 18:55",
        "waktu_scraping": "2024-05-12 19:33:37",
        "url": "https://news.republika.co.id/berita/sddfs9425/penyebab-suhu-panas-di-bengkulu-ternyata-karena-ada-gangguan-di-hindia-barat"
    },
    {
        "judul": "Ratusan Calhaj Yogyakarta Siap ke Tanah Suci, Pj Wali Kota Pesan Jaga Kesehatan",
        "kategori": "Rejogja",
        "waktu_publish": "12 May 2024, 18:48",
        "waktu_scraping": "2024-05-12 19:33:37",
        "url": "https://rejogja.republika.co.id/berita/sddfg9432/ratusan-calhaj-yogyakarta-siap-ke-tanah-suci-pj-wali-kota-pesan-jaga-kesehatan"
    },
    {
        "judul": "Harry Kane Terpaksa Absen di Laga Kandang Terakhir Munchen",
        "kategori": "Sport",
        "waktu_publish": "12 May 2024, 18:46",
        "waktu_scraping": "2024-05-12 19:33:37",
        "url": "https://sport.republika.co.id/berita/sddfdd456/harry-kane-terpaksa-absen-di-laga-kandang-terakhir-munchen"
    },
    {
        "judul": "Sholawat Badar Sambut Kedatangan Kloter Pertama Jamaah Haji Indonesia di Madinah",
        "kategori": "Ihram",
        "waktu_publish": "12 May 2024, 18:43",
        "waktu_scraping": "2024-05-12 19:33:37",
        "url": "https://ihram.republika.co.id/berita/sddf8c313/sholawat-badar-sambut-kedatangan-kloter-pertama-jamaah-haji-indonesia-di-madinah"
    },
    {
        "judul": "Polwan Polres Indramayu Sigap Layani Calhaj Asal Kota Bandung",
        "kategori": "Rejabar",
        "waktu_publish": "12 May 2024, 18:39",
        "waktu_scraping": "2024-05-12 19:33:37",
        "url": "https://rejabar.republika.co.id/berita/sddf1l463/polwan-polres-indramayu-sigap-layani-calhaj-asal-kota-bandung"
    },
    {
        "judul": "Video Terbaru RIIZE Buat Fans Marah, Ada Apa?",
        "kategori": "Ameera",
        "waktu_publish": "12 May 2024, 18:36",
        "waktu_scraping": "2024-05-12 19:33:37",
        "url": "https://ameera.republika.co.id/berita/sddew2425/video-terbaru-riize-buat-fans-marah-ada-apa"
    },
    {
        "judul": "Cyber University Tandatangani Kerja Sama Program Praktisi Mengajar",
        "kategori": "News",
        "waktu_publish": "12 May 2024, 18:35",
        "waktu_scraping": "2024-05-12 19:33:37",
        "url": "https://news.republika.co.id/berita/sddeuc463/cyber-university-tandatangani-kerja-sama-program-praktisi-mengajar"
    },
    {
        "judul": "393 Jamaah Haji Indonesia Kloter 1 Tiba di Madinah",
        "kategori": "Ihram",
        "waktu_publish": "12 May 2024, 18:32",
        "waktu_scraping": "2024-05-12 19:33:37",
        "url": "https://ihram.republika.co.id/berita/sddeqe349/393-jamaah-haji-indonesia-kloter-1-tiba-di-madinah"
    },
    {
        "judul": "Sebanyak 32 Korban Luka Kecelakaan Bus Subang Dibawa ke RS Depok",
        "kategori": "News",
        "waktu_publish": "12 May 2024, 18:31",
        "waktu_scraping": "2024-05-12 19:33:37",
        "url": "https://news.republika.co.id/berita/sddbop436/sebanyak-32-korban-luka-kecelakaan-bus-subang-dibawa-ke-rs-depok"
    },
    {
        "judul": "Kecelakaan Bus Ciater: Memahami Akar Masalah dan Solusi Mendesak Keselamatan Transportasi",
        "kategori": "News",
        "waktu_publish": "12 May 2024, 18:24",
        "waktu_scraping": "2024-05-12 19:33:37",
        "url": "https://news.republika.co.id/berita/sddec4349/kecelakaan-bus-ciater-memahami-akar-masalah-dan-solusi-mendesak-keselamatan-transportasi"
    },
    {
        "judul": "Kunjungi UEA, Gibran Laporan Soal Dana Hibah ke Mohammed bin Zayed",
        "kategori": "Rejogja",
        "waktu_publish": "12 May 2024, 18:23",
        "waktu_scraping": "2024-05-12 19:33:37",
        "url": "https://rejogja.republika.co.id/berita/sddebo432/kunjungi-uea-gibran-laporan-soal-dana-hibah-ke-mohammed-bin-zayed"
    },
    {
        "judul": "Lima Orang Tewas dalam Serangan Ukraina ke Belgorod",
        "kategori": "Internasional",
        "waktu_publish": "12 May 2024, 18:09",
        "waktu_scraping": "2024-05-12 19:33:37",
        "url": "https://internasional.republika.co.id/berita/sdddon488/lima-orang-tewas-dalam-serangan-ukraina-ke-belgorod"
    },
    {
        "judul": "Tank-tank Israel Masuk ke Kamp Pengungsi Jabalia",
        "kategori": "Internasional",
        "waktu_publish": "12 May 2024, 18:05",
        "waktu_scraping": "2024-05-12 19:33:37",
        "url": "https://internasional.republika.co.id/berita/sdddhp488/tanktank-israel-masuk-ke-kamp-pengungsi-jabalia"
    },
    {
        "judul": "Ini Alasan Ancelotti Enggan Tanggapi Presiden Prancis Soal Mbappe",
        "kategori": "Sport",
        "waktu_publish": "12 May 2024, 18:04",
        "waktu_scraping": "2024-05-12 19:33:37",
        "url": "https://sport.republika.co.id/berita/sddcgw456/ini-alasan-ancelotti-enggan-tanggapi-presiden-prancis-soal-mbappe"
    },
    {
        "judul": "Polda Sulteng Pastikan Anggota Ditpolairud Aniaya Warga Diproses Hukum",
        "kategori": "News",
        "waktu_publish": "12 May 2024, 18:03",
        "waktu_scraping": "2024-05-12 19:33:37",
        "url": "https://news.republika.co.id/berita/sddbiv436/polda-sulteng-pastikan-anggota-ditpolairud-aniaya-warga-diproses-hukum"
    },
    {
        "judul": "Bela Palestina, Ratusan Warga di Jepang Ikuti The Intifada March",
        "kategori": "Internasional",
        "waktu_publish": "12 May 2024, 17:56",
        "waktu_scraping": "2024-05-12 19:33:37",
        "url": "https://internasional.republika.co.id/berita/sddd1c488/bela-palestina-ratusan-warga-di-jepang-ikuti-the-intifada-march"
    },
    {
        "judul": "40 Ribu Wisatawan Kunjungi Monas pada Momen Libur Panjang Ini",
        "kategori": "News",
        "waktu_publish": "12 May 2024, 17:55",
        "waktu_scraping": "2024-05-12 19:33:37",
        "url": "https://news.republika.co.id/berita/sddd0e425/40-ribu-wisatawan-kunjungi-monas-pada-momen-libur-panjang-ini"
    },
    {
        "judul": "Ketum PSSI Dukung Langsung Perjuangan Timnas Putri",
        "kategori": "Sport",
        "waktu_publish": "12 May 2024, 17:48",
        "waktu_scraping": "2024-05-12 19:33:37",
        "url": "https://sport.republika.co.id/berita/sddcbr456/ketum-pssi-dukung-langsung-perjuangan-timnas-putri"
    },
    {
        "judul": "Keluarga Korban Kecelakaan Ciater Keluhkan Kondisi Bus tak Terawat",
        "kategori": "News",
        "waktu_publish": "12 May 2024, 17:45",
        "waktu_scraping": "2024-05-12 19:33:37",
        "url": "https://news.republika.co.id/berita/sddaq1436/keluarga-korban-kecelakaan-ciater-keluhkan-kondisi-bus-tak-terawat"
    },
    {
        "judul": "Sudah Berusia 36 Tahun, Djokovic Masih Berpotensi Pertahankan Peringkat 1 Dunia",
        "kategori": "Sport",
        "waktu_publish": "12 May 2024, 17:33",
        "waktu_scraping": "2024-05-12 19:33:37",
        "url": "https://sport.republika.co.id/berita/sddbz8456/sudah-berusia-36-tahun-djokovic-masih-berpotensi-pertahankan-peringkat-1-dunia"
    },
    {
        "judul": "RSUI Rawat Tujuh Pasien Korban Kecelakaan di Subang",
        "kategori": "News",
        "waktu_publish": "12 May 2024, 17:28",
        "waktu_scraping": "2024-05-12 19:33:37",
        "url": "https://news.republika.co.id/berita/sddaix436/rsui-rawat-tujuh-pasien-korban-kecelakaan-di-subang"
    },
    {
        "judul": "Kemenhub Terjunkan Tim Khusus Selidiki Penyebab Kecelakaan Bus di Ciater Subang",
        "kategori": "News",
        "waktu_publish": "12 May 2024, 17:26",
        "waktu_scraping": "2024-05-12 19:33:37",
        "url": "https://news.republika.co.id/berita/sddbnj425/kemenhub-terjunkan-tim-khusus-selidiki-penyebab-kecelakaan-bus-di-ciater-subang"
    },
    {
        "judul": "Konvoi Brigade Joxzin, Polresta Kerahkan Ratusan Personel untuk Pengamanan",
        "kategori": "News",
        "waktu_publish": "12 May 2024, 17:15",
        "waktu_scraping": "2024-05-12 19:33:37",
        "url": "https://news.republika.co.id/berita/sddad4436/konvoi-brigade-joxzin-polresta-kerahkan-ratusan-personel-untuk-pengamanan"
    },
    {
        "judul": "Terungkap Bus Wisata Pelajar SMK Lingga Kencana Bukan Bus Depok",
        "kategori": "Network",
        "waktu_publish": "12 May 2024, 17:09",
        "waktu_scraping": "2024-05-12 19:33:37",
        "url": "https://ruzka.republika.co.id/news/1674643486/terungkap-bus-wisata-pelajar-smk-lingga-kencana-bukan-bus-depok"
    },
    {
        "judul": "Libur Panjang Kali Ini, KCIC Berangkatkan 78 Ribu Penumpang",
        "kategori": "News",
        "waktu_publish": "12 May 2024, 17:06",
        "waktu_scraping": "2024-05-12 19:33:37",
        "url": "https://news.republika.co.id/berita/sddarh488/libur-panjang-kali-ini-kcic-berangkatkan-78-ribu-penumpang"
    },
    {
        "judul": "Tiga Orang Kembalikan Berkas Pendaftaran Bacabup ke PDIP Jember",
        "kategori": "Pemilu Kita",
        "waktu_publish": "12 May 2024, 17:02",
        "waktu_scraping": "2024-05-12 19:33:37",
        "url": "https://pemilukita.republika.co.id/berita/sdd9un436/tiga-orang-kembalikan-berkas-pendaftaran-bacabup-ke-pdip-jember"
    },
    {
        "judul": "Korban Meninggal Terdampak Banjir Sumbar Bertambah, Kini Jadi 27 Orang",
        "kategori": "News",
        "waktu_publish": "12 May 2024, 16:59",
        "waktu_scraping": "2024-05-12 19:33:37",
        "url": "https://news.republika.co.id/berita/sdd9bc436/korban-meninggal-terdampak-banjir-sumbar-bertambah-kini-jadi-27-orang"
    },
    {
        "judul": "Ada VAR di Championship Series Liga 1, Ini Antusiasme Madura United",
        "kategori": "Sport",
        "waktu_publish": "12 May 2024, 16:58",
        "waktu_scraping": "2024-05-12 19:33:37",
        "url": "https://sport.republika.co.id/berita/sdd9cv456/ada-var-di-championship-series-liga-1-ini-antusiasme-madura-united"
    },
    {
        "judul": "China Tegaskan Dukungan Pembangunan Sentralitas ASEAN",
        "kategori": "Internasional",
        "waktu_publish": "12 May 2024, 16:57",
        "waktu_scraping": "2024-05-12 19:33:37",
        "url": "https://internasional.republika.co.id/berita/sddabd488/china-tegaskan-dukungan-pembangunan-sentralitas-asean"
    },
    {
        "judul": "Lisa Blackpink Ingat Masa Lalu Saat Jadi Trainee: Aku Diam-Diam Menangis di Tempat Tidur",
        "kategori": "Ameera",
        "waktu_publish": "12 May 2024, 16:52",
        "waktu_scraping": "2024-05-12 19:33:37",
        "url": "https://ameera.republika.co.id/berita/sdda3z425/lisa-blackpink-ingat-masa-lalu-saat-jadi-trainee-aku-diamdiam-menangis-di-tempat-tidur"
    },
    {
        "judul": "KNKT Minta Publik dan Sekolah Buat Rencana Perjalanan yang Baik",
        "kategori": "News",
        "waktu_publish": "12 May 2024, 16:50",
        "waktu_scraping": "2024-05-12 19:33:37",
        "url": "https://news.republika.co.id/berita/sdda0v488/knkt-minta-publik-dan-sekolah-buat-rencana-perjalanan-yang-baik"
    },
    {
        "judul": "Pemakaman Jenazah Kecelakaan SMK Lingga Kencana Selesai, Siswa Masih Padati Makam",
        "kategori": "News",
        "waktu_publish": "12 May 2024, 16:50",
        "waktu_scraping": "2024-05-12 19:33:37",
        "url": "https://news.republika.co.id/berita/sdda0g468/pemakaman-jenazah-kecelakaan-smk-lingga-kencana-selesai-siswa-masih-padati-makam"
    },
    {
        "judul": "Gerindra: Revisi UU Kementerian Bisa Sebelum Pelantikan Presiden",
        "kategori": "News",
        "waktu_publish": "12 May 2024, 16:46",
        "waktu_scraping": "2024-05-12 19:33:37",
        "url": "https://news.republika.co.id/berita/sdd90i436/gerindra-revisi-uu-kementerian-bisa-sebelum-pelantikan-presiden"
    },
    {
        "judul": "Bertambah, 80 Jasad Ditemukan di Kuburan Massal Kompleks Al-Shifa Gaza",
        "kategori": "Internasional",
        "waktu_publish": "12 May 2024, 16:46",
        "waktu_scraping": "2024-05-12 19:33:37",
        "url": "https://internasional.republika.co.id/berita/sdd9so488/bertambah-80-jasad-ditemukan-di-kuburan-massal-kompleks-alshifa-gaza"
    },
    {
        "judul": "1.200 Guru PAUD di Banyuwangi Dapat Insentif, Anggaran Rp 7,2 Miliar",
        "kategori": "Rejogja",
        "waktu_publish": "12 May 2024, 16:45",
        "waktu_scraping": "2024-05-12 19:33:37",
        "url": "https://rejogja.republika.co.id/berita/sdd9s2432/1200-guru-paud-di-banyuwangi-dapat-insentif-anggaran-rp-72-miliar"
    },
    {
        "judul": "Kemenhub Minta Masyarakat Tolak Gunakan Bus tak Punya Izin Jalan",
        "kategori": "News",
        "waktu_publish": "12 May 2024, 16:39",
        "waktu_scraping": "2024-05-12 19:33:37",
        "url": "https://news.republika.co.id/berita/sdd9hv488/kemenhub-minta-masyarakat-tolak-gunakan-bus-tak-punya-izin-jalan"
    },
    {
        "judul": "Putri Politikus Senior PDIP Aria Bima Daftar Pilkada Solo",
        "kategori": "Pemilu Kita",
        "waktu_publish": "12 May 2024, 16:35",
        "waktu_scraping": "2024-05-12 19:33:37",
        "url": "https://pemilukita.republika.co.id/berita/sdd8v5436/putri-politikus-senior-pdip-aria-bima-daftar-pilkada-solo"
    },
    {
        "judul": "Hamas: AS Bertanggung Jawab Atas Serangan Israel ke Rafah",
        "kategori": "Internasional",
        "waktu_publish": "12 May 2024, 16:26",
        "waktu_scraping": "2024-05-12 19:33:37",
        "url": "https://internasional.republika.co.id/berita/sdd8vn488/hamas-as-bertanggung-jawab-atas-serangan-israel-ke-rafah"
    },
    {
        "judul": "Jangan Lewatkan, Jadwal dan Prediksi Starting XI MU Vs Arsenal Malam Ini",
        "kategori": "Sport",
        "waktu_publish": "12 May 2024, 16:25",
        "waktu_scraping": "2024-05-12 19:33:37",
        "url": "https://sport.republika.co.id/berita/sdd8u4456/jangan-lewatkan-jadwal-dan-prediksi-starting-xi-mu-vs-arsenal-malam-ini"
    },
    {
        "judul": "Ingat Pesan Eyang, Putri Politisi PDIP Daftar Bakal Calon Wakil Wali Kota Solo",
        "kategori": "Rejogja",
        "waktu_publish": "12 May 2024, 16:23",
        "waktu_scraping": "2024-05-12 19:33:37",
        "url": "https://rejogja.republika.co.id/berita/sdd8rs432/ingat-pesan-eyang-putri-politisi-pdip-daftar-bakal-calon-wakil-wali-kota-solo"
    }
]