[
    {
        "judul": "Liverpool Hajar Tottenham Hotspur 4-2, Tetap di Peringkat Tiga Klasemen Liga Inggris",
        "kategori": "Sport",
        "waktu_publish": "4 detik yang lalu",
        "waktu_scraping": "2024-05-06 06:17:03",
        "url": "https://sport.republika.co.id/berita/sd1cob348/liverpool-hajar-tottenham-hotspur-42-tetap-di-peringkat-tiga-klasemen-liga-inggris"
    },
    {
        "judul": "Hamas Bombardir Pos Komando Israel, Tiga Tewas Belasan Terluka",
        "kategori": "Internasional",
        "waktu_publish": "4 menit yang lalu",
        "waktu_scraping": "2024-05-06 06:17:03",
        "url": "https://internasional.republika.co.id/berita/sd1ci0393/hamas-bombardir-pos-komando-israel-tiga-tewas-belasan-terluka"
    },
    {
        "judul": "Laga AS Roma Vs Juventus Berakhir tanpa Pemenang",
        "kategori": "Sport",
        "waktu_publish": "10 menit yang lalu",
        "waktu_scraping": "2024-05-06 06:17:03",
        "url": "https://sport.republika.co.id/berita/sd1c75348/laga-as-roma-vs-juventus-berakhir-tanpa-pemenang"
    },
    {
        "judul": "Terungkap: Netanyahu Secara Pribadi Halangi Gencatan Senjata",
        "kategori": "Internasional",
        "waktu_publish": "12 menit yang lalu",
        "waktu_scraping": "2024-05-06 06:17:03",
        "url": "https://www.republika.id/posts/52538/terungkap-netanyahu-secara-pribadi-halangi-gencatan-senjata"
    },
    {
        "judul": "Ibarat Pedang Bermata Dua, Begini Manfaat dan Risiko Paylater",
        "kategori": "Network",
        "waktu_publish": "14 menit yang lalu",
        "waktu_scraping": "2024-05-06 06:17:03",
        "url": "https://impresi.republika.co.id/didaktika/1694620655/ibarat-pedang-bermata-dua-begini-manfaat-dan-risiko-paylater"
    },
    {
        "judul": "Segala Bentuk Perbuatan di Dunia Diawasi Allah, Begini Penjelasan Ulama Turki",
        "kategori": "Islam Digest",
        "waktu_publish": "16 menit yang lalu",
        "waktu_scraping": "2024-05-06 06:17:03",
        "url": "https://islamdigest.republika.co.id/berita/sd1bxb430/segala-bentuk-perbuatan-di-dunia-diawasi-allah-begini-penjelasan-ulama-turki"
    },
    {
        "judul": "7 Fakta dan Mitos Konstelasi Aries, Rasi Bintang Kecil Domba Berbulu Emas",
        "kategori": "Network",
        "waktu_publish": "24 menit yang lalu",
        "waktu_scraping": "2024-05-06 06:17:03",
        "url": "https://antariksa.republika.co.id/ulasan/1714620642/7-fakta-dan-mitos-konstelasi-aries-rasi-bintang-kecil-domba-berbulu-emas"
    },
    {
        "judul": "KKB Serang Gereja dan Rampas Barang Milik Jemaat di Pegunungan Bintang",
        "kategori": "News",
        "waktu_publish": "26 menit yang lalu",
        "waktu_scraping": "2024-05-06 06:17:03",
        "url": "https://news.republika.co.id/berita/sd1bhu377/kkb-serang-gereja-dan-rampas-barang-milik-jemaat-di-pegunungan-bintang"
    },
    {
        "judul": "Dewan Keamanan Israel: Perang di Gaza Jalan Buntu",
        "kategori": "Internasional",
        "waktu_publish": "32 menit yang lalu",
        "waktu_scraping": "2024-05-06 06:17:03",
        "url": "https://www.republika.id/posts/52540/dewan-keamanan-israel-perang-di-gaza-jalan-buntu"
    },
    {
        "judul": "Zikir Pagi untuk Melindungi Diri dari Pagi Hingga Petang",
        "kategori": "Khazanah",
        "waktu_publish": "36 menit yang lalu",
        "waktu_scraping": "2024-05-06 06:17:03",
        "url": "https://www.republika.id/posts/52549/zikir-pagi-untuk-melindungi-diri-dari-pagi-hingga-petang"
    },
    {
        "judul": "Pejuang Palestina Bombardir Markas Komando Israel di Gaza",
        "kategori": "Internasional",
        "waktu_publish": "39 menit yang lalu",
        "waktu_scraping": "2024-05-06 06:17:03",
        "url": "https://www.republika.id/posts/52548/pejuang-palestina-bombardir-markas-komando-israel-di-gaza"
    },
    {
        "judul": "Bos Tembaga Ditemukan Tewas Dibunuh Teman Kencan Sesama Jenisnya,",
        "kategori": "News",
        "waktu_publish": "40 menit yang lalu",
        "waktu_scraping": "2024-05-06 06:17:03",
        "url": "https://news.republika.co.id/berita/sd1ath377/bos-tembaga-ditemukan-tewas-dibunuh-teman-kencan-sesama-jenisnya"
    },
    {
        "judul": "Ketahuan Pakai Visa Non Haji Jamaah Bisa Dideportasi dan 10 Tahun Dilarang Masuk ke Saudi",
        "kategori": "Ihram",
        "waktu_publish": "1 jam yang lalu",
        "waktu_scraping": "2024-05-06 06:17:03",
        "url": "https://ihram.republika.co.id/berita/sd12eo282/ketahuan-pakai-visa-non-haji-jamaah-bisa-dideportasi-dan-10-tahun-dilarang-masuk-ke-saudi"
    },
    {
        "judul": "Kalau Beda Agama, Apakah Pernikahan Rizky Febian-Mahalini Sah Menurut Islam?",
        "kategori": "Ameera",
        "waktu_publish": "1 jam yang lalu",
        "waktu_scraping": "2024-05-06 06:17:03",
        "url": "https://ameera.republika.co.id/berita/sczvhp414/kalau-beda-agama-apakah-pernikahan-rizky-febianmahalini-sah-menurut-islam"
    },
    {
        "judul": "Gamers Vior Cerita Soal Virus di Otak, Sebut Ibunya Suka Makan Makanan Mentah Saat Hamil",
        "kategori": "Ameera",
        "waktu_publish": "1 jam yang lalu",
        "waktu_scraping": "2024-05-06 06:17:03",
        "url": "https://ameera.republika.co.id/berita/sd0xm7425/gamers-vior-cerita-soal-virus-di-otak-sebut-ibunya-suka-makan-makanan-mentah-saat-hamil"
    },
    {
        "judul": "22 Kloter Haji Berangkat Perdana pada 12 Mei 2024",
        "kategori": "Ihram",
        "waktu_publish": "1 jam yang lalu",
        "waktu_scraping": "2024-05-06 06:17:03",
        "url": "https://ihram.republika.co.id/berita/sd18rr451/22-kloter-haji-berangkat-perdana-pada-12-mei-2024"
    },
    {
        "judul": "Ajang OlympiAR 2024 Alami Kenaikan Jumlah Peserta Hingga 290 Persen",
        "kategori": "Rejogja",
        "waktu_publish": "1 jam yang lalu",
        "waktu_scraping": "2024-05-06 06:17:03",
        "url": "https://rejogja.republika.co.id/berita/sd18pt291/ajang-olympiar-2024-alami-kenaikan-jumlah-peserta-hingga-290-persen"
    },
    {
        "judul": "BKPM: Solo Great Sale Buka Peluang Investasi Baru",
        "kategori": "News",
        "waktu_publish": "1 jam yang lalu",
        "waktu_scraping": "2024-05-06 06:17:03",
        "url": "https://news.republika.co.id/berita/sd18li451/bkpm-solo-great-sale-buka-peluang-investasi-baru"
    },
    {
        "judul": "Baca Dzikir Pagi Ini dan Rasakan Dampaknya Seharian",
        "kategori": "Iqra",
        "waktu_publish": "2 jam yang lalu",
        "waktu_scraping": "2024-05-06 06:17:03",
        "url": "https://iqra.republika.co.id/berita/sd181v430/baca-dzikir-pagi-ini-dan-rasakan-dampaknya-seharian"
    },
    {
        "judul": "Pakai Baju Berwarna Saat Umroh dan Haji, Bolehkah?",
        "kategori": "Ameera",
        "waktu_publish": "2 jam yang lalu",
        "waktu_scraping": "2024-05-06 06:17:03",
        "url": "https://ameera.republika.co.id/berita/sd0wti425/pakai-baju-berwarna-saat-umroh-dan-haji-bolehkah"
    },
    {
        "judul": "Deretan Fadhilah yang Diperoleh Jika Baca Kalimat Tahlil sebagai Dzikir Pagi",
        "kategori": "Iqra",
        "waktu_publish": "2 jam yang lalu",
        "waktu_scraping": "2024-05-06 06:17:03",
        "url": "https://iqra.republika.co.id/berita/sd17wh430/deretan-fadhilah-yang-diperoleh-jika-baca-kalimat-tahlil-sebagai-dzikir-pagi"
    },
    {
        "judul": "Kapan Wartawan Datang ke Perpustakaan? (Artikel Hari Buku Sedunia yang Terlambat)",
        "kategori": "Network",
        "waktu_publish": "2 jam yang lalu",
        "waktu_scraping": "2024-05-06 06:17:03",
        "url": "https://kingdomsriwijaya.id/posts/303322/kapan-wartawan-datang-ke-perpustakaan-artikel-hari-buku-sedunia-yang-terlambat-"
    },
    {
        "judul": "3 Kasus Pencucian Uang Kripto Terbesar di Dunia, Diretas Lalu Dibelikan Kripto Lagi",
        "kategori": "Network",
        "waktu_publish": "3 jam yang lalu",
        "waktu_scraping": "2024-05-06 06:17:03",
        "url": "https://genpop.republika.co.id/posts/305137/3-kasus-pencucian-uang-kripto-terbesar-di-dunia-diretas-lalu-dibelikan-kripto-lagi"
    },
    {
        "judul": "Refleksi Hardiknas",
        "kategori": "Retizen",
        "waktu_publish": "3 jam yang lalu",
        "waktu_scraping": "2024-05-06 06:17:03",
        "url": "https://retizen.republika.co.id/posts/305106/refleksi-hardiknas"
    },
    {
        "judul": "Pede Banget, Trader Senior Ini Sebut Bitcoin sebagai Satu-satunya Aset Kripto",
        "kategori": "Network",
        "waktu_publish": "3 jam yang lalu",
        "waktu_scraping": "2024-05-06 06:17:03",
        "url": "https://genpop.republika.co.id/posts/305136/pede-banget-trader-senior-ini-sebut-bitcoin-sebagai-satu-satunya-aset-kripto"
    },
    {
        "judul": "Kuota Haji Terpenuhi, Kemenag Imbau Masyarakat tidak Tertipu Tawaran Visa Non Haji",
        "kategori": "Ihram",
        "waktu_publish": "4 jam yang lalu",
        "waktu_scraping": "2024-05-06 06:17:03",
        "url": "https://ihram.republika.co.id/berita/sd11tw282/kuota-haji-terpenuhi-kemenag-imbau-masyarakat-tidak-tertipu-tawaran-visa-non-haji"
    },
    {
        "judul": "Pengamat Nilai PAN Harus Ubah Citra Zita Anjani Jika Ingin Mengusungnya di Pilgub Jakarta",
        "kategori": "News",
        "waktu_publish": "5 jam yang lalu",
        "waktu_scraping": "2024-05-06 06:17:03",
        "url": "https://news.republika.co.id/berita/sd0apx409/pengamat-nilai-pan-harus-ubah-citra-zita-anjani-jika-ingin-mengusungnya-di-pilgub-jakarta"
    },
    {
        "judul": "Pengamat Nilai Presidential Club Upaya Prabowo Rekonsiliasikan Presiden-Presiden Terdahulu",
        "kategori": "News",
        "waktu_publish": "6 jam yang lalu",
        "waktu_scraping": "2024-05-06 06:17:03",
        "url": "https://news.republika.co.id/berita/sd0aiv409/pengamat-nilai-presidential-club-upaya-prabowo-rekonsiliasikan-presidenpresiden-terdahulu"
    },
    {
        "judul": "Puasa Gelar 16 Tahun, Tim Uber Indonesia Raih Medali Perak di Piala Uber 2024",
        "kategori": "Network",
        "waktu_publish": "6 jam yang lalu",
        "waktu_scraping": "2024-05-06 06:17:03",
        "url": "https://badmintonews.id/posts/305115/puasa-gelar-16-tahun-tim-uber-indonesia-raih-medali-perak-di-piala-uber-2024"
    },
    {
        "judul": "Piala Thomas 2024: King Jojo Tak Terkalahkan",
        "kategori": "Network",
        "waktu_publish": "6 jam yang lalu",
        "waktu_scraping": "2024-05-06 06:17:03",
        "url": "https://badmintonews.id/posts/305120/piala-thomas-2024-king-jojo-tak-terkalahkan"
    },
    {
        "judul": "Ribuan Buruh Rayakan May Day dengan Berdialog Bersama Pemkot Bandung",
        "kategori": "Network",
        "waktu_publish": "6 jam yang lalu",
        "waktu_scraping": "2024-05-06 06:17:03",
        "url": "https://bandung24jam.id/posts/305132/ribuan-buruh-rayakan-may-day-dengan-berdialog-bersama-pemkot-bandung"
    },
    {
        "judul": "Piala Thomas 2024: Kalah 1-3, Indonesia Kawinkan Medali Perak",
        "kategori": "Network",
        "waktu_publish": "6 jam yang lalu",
        "waktu_scraping": "2024-05-06 06:17:03",
        "url": "https://badmintonews.id/posts/305131/piala-thomas-2024-kalah-1-3-indonesia-kawinkan-medali-perak"
    },
    {
        "judul": "Menikmati Beragam Fitur Canggih yang Minim Tombol di Wuling Cloud EV",
        "kategori": "Ekonomi",
        "waktu_publish": "6 jam yang lalu",
        "waktu_scraping": "2024-05-06 06:17:03",
        "url": "https://ekonomi.republika.co.id/berita/sd0tqg468/menikmati-beragam-fitur-canggih-yang-minim-tombol-di-wuling-cloud-ev"
    },
    {
        "judul": "Ratusan Orang Demo di Depan Kemenlu Swedia, Desak Eurovision Song Contest Boikot Israel",
        "kategori": "Ameera",
        "waktu_publish": "6 jam yang lalu",
        "waktu_scraping": "2024-05-06 06:17:03",
        "url": "https://ameera.republika.co.id/berita/sd0dja414/ratusan-orang-demo-di-depan-kemenlu-swedia-desak-eurovision-song-contest-boikot-israel"
    },
    {
        "judul": "BMKG Prediksi akan Ada Peningkatan Suhu Panas pada Juli-Agustus",
        "kategori": "Video",
        "waktu_publish": "6 jam yang lalu",
        "waktu_scraping": "2024-05-06 06:17:03",
        "url": "https://tv.republika.co.id/berita/sd0va7418/bmkg-prediksi-akan-ada-peningkatan-suhu-panas-pada-juliagustus"
    },
    {
        "judul": "Shiba Inu, Altcoin yang Mengalami Kenaikan Drastis di Tengah Gejolak Kripto",
        "kategori": "Network",
        "waktu_publish": "6 jam yang lalu",
        "waktu_scraping": "2024-05-06 06:17:03",
        "url": "https://genpop.republika.co.id/posts/305135/shiba-inu-altcoin-yang-mengalami-kenaikan-drastis-di-tengah-gejolak-kripto"
    },
    {
        "judul": "Melestarikan Permainan Tradisional, Anak-anak Adu Cepat Balap Geledekan",
        "kategori": "Visual",
        "waktu_publish": "6 jam yang lalu",
        "waktu_scraping": "2024-05-06 06:17:03",
        "url": "https://visual.republika.co.id/berita/sd0usi491/melestarikan-permainan-tradisional-anakanak-adu-cepat-balap-geledekan"
    },
    {
        "judul": "Musim Kemarau di Indonesia Terjadi Mulai Mei, Ini Tips Hadapi Suhu Panas",
        "kategori": "News",
        "waktu_publish": "6 jam yang lalu",
        "waktu_scraping": "2024-05-06 06:17:03",
        "url": "https://news.republika.co.id/berita/sd0uz8425/musim-kemarau-di-indonesia-terjadi-mulai-mei-ini-tips-hadapi-suhu-panas"
    },
    {
        "judul": "Otorita Danau Toba Harap Trail of The Kings Bisa Tembus Daftar UTMB",
        "kategori": "Ekonomi",
        "waktu_publish": "6 jam yang lalu",
        "waktu_scraping": "2024-05-06 06:17:03",
        "url": "https://ekonomi.republika.co.id/berita/sd0usx490/otorita-danau-toba-harap-trail-of-the-kings-bisa-tembus-daftar-utmb"
    },
    {
        "judul": "Produktivitas Kedelai di Banyumas Diharapkan Capai 1,5-1,7 Ton per Hektare",
        "kategori": "Rejogja",
        "waktu_publish": "6 jam yang lalu",
        "waktu_scraping": "2024-05-06 06:17:03",
        "url": "https://rejogja.republika.co.id/berita/sd0url432/produktivitas-kedelai-di-banyumas-diharapkan-capai-1517-ton-per-hektare"
    },
    {
        "judul": "Gunung Semeru 2 Kali Erupsi Hari Ini, Letusan Abu Hingga 1.000 Meter",
        "kategori": "News",
        "waktu_publish": "7 jam yang lalu",
        "waktu_scraping": "2024-05-06 06:17:03",
        "url": "https://news.republika.co.id/berita/sd0un6425/gunung-semeru-2-kali-erupsi-hari-ini-letusan-abu-hingga-1000-meter"
    },
    {
        "judul": "31 Tempat Outbound di Bandung yang Paling Seru",
        "kategori": "Network",
        "waktu_publish": "7 jam yang lalu",
        "waktu_scraping": "2024-05-06 06:17:03",
        "url": "https://genpop.republika.co.id/posts/305134/31-tempat-outbound-di-bandung-yang-paling-seru"
    },
    {
        "judul": "BI Maluku Perkuat Ekonomi Syariah Lewat Salam Fest 2024",
        "kategori": "Sharia",
        "waktu_publish": "7 jam yang lalu",
        "waktu_scraping": "2024-05-06 06:17:03",
        "url": "https://sharia.republika.co.id/berita/sd0ujy490/bi-maluku-perkuat-ekonomi-syariah-lewat-salam-fest-2024"
    },
    {
        "judul": "Indonesia Juara Kedua Piala Thomas 2024",
        "kategori": "Visual",
        "waktu_publish": "7 jam yang lalu",
        "waktu_scraping": "2024-05-06 06:17:03",
        "url": "https://visual.republika.co.id/berita/sd0ugk491/indonesia-juara-kedua-piala-thomas-2024"
    },
    {
        "judul": "Tangkap Tren Impact Investing, Ini Strategi Amartha",
        "kategori": "Ekonomi",
        "waktu_publish": "7 jam yang lalu",
        "waktu_scraping": "2024-05-06 06:17:03",
        "url": "https://ekonomi.republika.co.id/berita/sd0ubn490/tangkap-tren-impact-investing-ini-strategi-amartha"
    },
    {
        "judul": "Ritual Kawalu Badui Sudah Selesai, Wisatawan Domestik Dipersilakan Berkunjung Kembali",
        "kategori": "News",
        "waktu_publish": "7 jam yang lalu",
        "waktu_scraping": "2024-05-06 06:17:03",
        "url": "https://news.republika.co.id/berita/sd0u9q425/ritual-kawalu-badui-sudah-selesai-wisatawan-domestik-dipersilakan-berkunjung-kembali"
    },
    {
        "judul": "BSI Maslahat Salurkan Bantuan untuk Penyintas Banjir Bandang Luwu",
        "kategori": "Sharia",
        "waktu_publish": "7 jam yang lalu",
        "waktu_scraping": "2024-05-06 06:17:03",
        "url": "https://sharia.republika.co.id/berita/sd0u30490/bsi-maslahat-salurkan-bantuan-untuk-penyintas-banjir-bandang-luwu"
    },
    {
        "judul": "Operasi Jagratara, Imigrasi Kediri Sisir Tenaga Kerja Asing",
        "kategori": "Rejogja",
        "waktu_publish": "7 jam yang lalu",
        "waktu_scraping": "2024-05-06 06:17:03",
        "url": "https://rejogja.republika.co.id/berita/sd0tzu432/operasi-jagratara-imigrasi-kediri-sisir-tenaga-kerja-asing"
    },
    {
        "judul": "Riau Pecahkan Rekor Muri, Sajian 3.500 Mi Sagu Goreng Gratis untuk Masyarakat",
        "kategori": "News",
        "waktu_publish": "7 jam yang lalu",
        "waktu_scraping": "2024-05-06 06:17:03",
        "url": "https://news.republika.co.id/berita/sd0ty3425/riau-pecahkan-rekor-muri-sajian-3500-mi-sagu-goreng-gratis-untuk-masyarakat"
    },
    {
        "judul": "Sri Mulyani Temui Bos ADB Bahas Pendanaan Transisi Energi",
        "kategori": "Ekonomi",
        "waktu_publish": "7 jam yang lalu",
        "waktu_scraping": "2024-05-06 06:17:03",
        "url": "https://ekonomi.republika.co.id/berita/sd0twp490/sri-mulyani-temui-bos-adb-bahas-pendanaan-transisi-energi"
    }
]